build/lib/build/lib/build/lib/build/lib/build/lib/build/lib/build/lib/kuberfest/consts.py
build/lib/build/lib/build/lib/build/lib/build/lib/build/lib/build/lib/kuberfest/project.py
build/lib/build/lib/build/lib/build/lib/build/lib/build/lib/build/lib/kuberfest/run.py
build/lib/build/lib/build/lib/build/lib/build/lib/build/lib/dotnet_demo_project/kuberfest/functions.py
build/lib/build/lib/build/lib/build/lib/build/lib/build/lib/dotnet_demo_project/kuberfest/settings.py
build/lib/build/lib/build/lib/build/lib/build/lib/build/lib/dotnet_demo_project/kuberfest/variables.py
build/lib/build/lib/build/lib/build/lib/build/lib/build/lib/kuberfest/consts.py
build/lib/build/lib/build/lib/build/lib/build/lib/build/lib/kuberfest/project.py
build/lib/build/lib/build/lib/build/lib/build/lib/build/lib/kuberfest/run.py
build/lib/build/lib/build/lib/build/lib/build/lib/build/lib/kuberfest/commands/__init__.py
build/lib/build/lib/build/lib/build/lib/build/lib/build/lib/kuberfest/commands/build.py
build/lib/build/lib/build/lib/build/lib/build/lib/build/lib/kuberfest/commands/context.py
build/lib/build/lib/build/lib/build/lib/build/lib/build/lib/kuberfest/commands/delete.py
build/lib/build/lib/build/lib/build/lib/build/lib/build/lib/kuberfest/commands/deploy.py
build/lib/build/lib/build/lib/build/lib/build/lib/build/lib/kuberfest/commands/development.py
build/lib/build/lib/build/lib/build/lib/build/lib/build/lib/kuberfest/commands/init_db.py
build/lib/build/lib/build/lib/build/lib/build/lib/build/lib/kuberfest/commands/minikube_ip.py
build/lib/build/lib/build/lib/build/lib/build/lib/build/lib/kuberfest/commands/print_environment.py
build/lib/build/lib/build/lib/build/lib/build/lib/build/lib/kuberfest/commands/push.py
build/lib/build/lib/build/lib/build/lib/build/lib/build/lib/kuberfest/commands/start_minikube.py
build/lib/build/lib/build/lib/build/lib/build/lib/build/lib/kuberfest/tools/__init__.py
kuberfest-0.0.1a1.dist-info/METADATA
kuberfest-0.0.1a1.dist-info/RECORD
kuberfest-0.0.1a1.dist-info/WHEEL
kuberfest-0.0.1a1.dist-info/top_level.txt
