Metadata-Version: 2.1
Name: kuberfest
Version: 0.0.1a1
Summary: A lightweight framework for fast cloud development
Home-page: https://github.com/yanivp/kuberfest
Author: Yaniv Peer
Author-email: yanivpeer@gmail.com
License: UNKNOWN
Platform: UNKNOWN
Classifier: Programming Language :: Python :: 3
Classifier: License :: OSI Approved :: MIT License
Classifier: Operating System :: OS Independent
Requires-Dist: pyyaml
